{
    "/js/app.js": "/js/app.js",
    "/css/app.css": "/css/app.css",
    "/js/app.211956119347b4fb563a.hot-update.js": "/js/app.211956119347b4fb563a.hot-update.js",
    "/js/app.e4007ca313e0ccb096e9.hot-update.js": "/js/app.e4007ca313e0ccb096e9.hot-update.js",
    "/js/app.8bb38765bb1cfb3afa85.hot-update.js": "/js/app.8bb38765bb1cfb3afa85.hot-update.js",
    "/js/app.08059d42536e4fd8d534.hot-update.js": "/js/app.08059d42536e4fd8d534.hot-update.js",
    "/js/app.5af61af3033f13eb31eb.hot-update.js": "/js/app.5af61af3033f13eb31eb.hot-update.js"
}
